connector/__init__.py
connector/connector.py
bn_connector-0.0.2.dist-info/METADATA
bn_connector-0.0.2.dist-info/WHEEL
bn_connector-0.0.2.dist-info/top_level.txt
bn_connector-0.0.2.dist-info/RECORD
