Metadata-Version: 2.1
Name: bn_connector
Version: 0.0.2
Summary: API for microservices on byneuron backend
Home-page: https://gitlab.com/bynubian/bynode/python_packages/service-connector
Author: jovi
Author-email: jo.vinckier@bynubian.com
License: UNKNOWN
Platform: UNKNOWN
Classifier: Programming Language :: Python :: 3
Classifier: License :: OSI Approved :: MIT License
Classifier: Operating System :: OS Independent
Requires-Python: >=3.7
